setup.py
conttest/__init__.py
conttest/conttest.py
conttest.egg-info/PKG-INFO
conttest.egg-info/SOURCES.txt
conttest.egg-info/dependency_links.txt
conttest.egg-info/entry_points.txt
conttest.egg-info/top_level.txt