Metadata-Version: 1.0
Name: conttest
Version: 0.0.6
Summary: Simple continuous testing tool
Home-page: https://github.com/eigenhombre/continuous-testing-helper
Author: John Jacobsen
Author-email: john@mail.npxdesigns.com
License: MIT
Platform: UNKNOWN
